PeeweeZalomov/__init__.py
PeeweeZalomov/main.py
PeeweeZalomov/pw_goods_zal.py
peewee_tables_Zalomov-0.0.2.dist-info/LICENSE
peewee_tables_Zalomov-0.0.2.dist-info/METADATA
peewee_tables_Zalomov-0.0.2.dist-info/WHEEL
peewee_tables_Zalomov-0.0.2.dist-info/top_level.txt
peewee_tables_Zalomov-0.0.2.dist-info/RECORD
