Metadata-Version: 2.1
Name: peewee-tables-Zalomov
Version: 0.0.2
Summary: Just some fun things to do with your tables, test module, which doesn't contain anything useful
Home-page: https://github.com/BangerVanos/PeeWeeZal
Author: Roman Zalomov
Author-email: romchik349@gmail.com
License: UNKNOWN
Platform: UNKNOWN
Classifier: Programming Language :: Python :: 3.10
Classifier: License :: OSI Approved :: MIT License
Classifier: Operating System :: OS Independent
Requires-Python: >=3.8
License-File: LICENSE
